{
  "project_info": {
    "project_number": "727622772799",
    "project_id": "qrpicture-80247",
    "storage_bucket": "qrpicture-80247.firebasestorage.app"
  },
  "client": [
    {
      "client_info": {
        "mobilesdk_app_id": "1:727622772799:android:98df54fa173cc9f199708a",
        "android_client_info": {
          "package_name": "com.example.qrpicture"
        }
      },
      "oauth_client": [],
      "api_key": [
        {
          "current_key": "AIzaSyDOtboKXx6vch_nQxquhFyPRYyLGFdvGyM"
        }
      ],
      "services": {
        "appinvite_service": {
          "other_platform_oauth_client": []
        }
      }
    }
  ],
  "configuration_version": "1"
}